src/POTA_park_lookup.py
src/QRZ_XML_frontend.py
src/QRZ_output_ui.pyui
src/QRZ_xml_function.py
src/SOTA_summit_lookup.py
src/__init__.py
src/arctic_key.py
src/dd2grid.py
src/dms_convert.py
src/dms_convert_dd_ui.pyui
src/dms_convert_ddm_ui.pyui
src/dms_convert_dms_ui.pyui
src/dms_convert_frontend.py
src/dms_convert_ui.pyui
src/handie_bck.jpg
src/handie_ci.py
src/handie_ci_ui.pyui
src/handie_utils.py
src/handie_utils_ui.pyui
src/lat_lon_ui.pyui
src/lat_long_distance.py
src/lat_long_distance_calculate.py
handie_utils_package_wander99-4.0.dist-info/METADATA
handie_utils_package_wander99-4.0.dist-info/WHEEL
handie_utils_package_wander99-4.0.dist-info/licenses/LICENSE
handie_utils_package_wander99-4.0.dist-info/RECORD
