Metadata-Version: 2.1
Name: handie_utils_package_wander99
Version: 4.0
Summary: Handie utilities especially for POTA/SOTA operators
Author-email: George <georgefennLT@gmail.com>
License-File: LICENSE
Classifier: License :: OSI Approved :: MIT License
Classifier: Operating System :: iOS
Classifier: Programming Language :: Python :: 3
Requires-Python: >=3.7
